LICENSE
MANIFEST.in
README.md
setup.cfg
setup.py
carbonate/__init__.py
carbonate/aggregation.py
carbonate/cli.py
carbonate/cluster.py
carbonate/config.py
carbonate/fill.py
carbonate/list.py
carbonate/lookup.py
carbonate/sieve.py
carbonate/stale.py
carbonate/sync.py
carbonate/util.py
carbonate3.egg-info/PKG-INFO
carbonate3.egg-info/SOURCES.txt
carbonate3.egg-info/dependency_links.txt
carbonate3.egg-info/entry_points.txt
carbonate3.egg-info/requires.txt
carbonate3.egg-info/top_level.txt