Metadata-Version: 2.1
Name: carbonate3
Version: 1.1.5.dev1
Summary: Tools for managing federated carbon clusters.
Home-page: https://github.com/nimda7/carbonate3
Maintainer: Alex Klimenka
Maintainer-email: nimda7@gmail.com
License: MIT
Keywords: graphite carbon
Platform: UNKNOWN
Classifier: Development Status :: 3 - Alpha
Classifier: Environment :: Console
Classifier: Intended Audience :: System Administrators
Classifier: License :: OSI Approved :: MIT License
Classifier: Operating System :: OS Independent
Classifier: Programming Language :: Python :: 3
Classifier: Programming Language :: Python :: 3.6
Classifier: Topic :: System :: Monitoring
Classifier: Topic :: System :: Systems Administration
